distvae/__init__.py
distvae/__version__.py
distvae/utils.py
distvae/models/__init__.py
distvae/models/resnet.py
distvae/models/upsampling.py
distvae/models/vae.py
distvae/models/layers/__init__.py
distvae/models/layers/conv2d.py
distvae/models/layers/normalization.py
distvae/models/unets/__init__.py
distvae/models/unets/unet_2d_blocks.py
distvae/modules/__init__.py
distvae/modules/patch_utils.py
distvae/modules/adapters/__init__.py
distvae/modules/adapters/resnet_adapters.py
distvae/modules/adapters/upsampling_adapters.py
distvae/modules/adapters/layers/__init__.py
distvae/modules/adapters/layers/conv_adapters.py
distvae/modules/adapters/layers/norm_adapters.py
distvae/modules/adapters/unets/__init__.py
distvae/modules/adapters/unets/unet_2d_blocks_adapters.py
distvae/modules/adapters/vae/__init__.py
distvae/modules/adapters/vae/decoder_adapters.py
DistVAE-0.0.0b5.dist-info/LICENSE.txt
DistVAE-0.0.0b5.dist-info/METADATA
DistVAE-0.0.0b5.dist-info/WHEEL
DistVAE-0.0.0b5.dist-info/top_level.txt
DistVAE-0.0.0b5.dist-info/RECORD
