Metadata-Version: 2.2
Name: DistVAE
Version: 0.0.0b5
Summary: DistVAE: Patch Parallelism Distributed VAE for High-Resolution image generation
Home-page: https://github.com/xdit-project/DistVAE.
Author: Jinzhe Pan
Author-email: eigensystem1318@gmail.com
Classifier: Programming Language :: Python :: 3
Classifier: Operating System :: OS Independent
Requires-Python: >=3.10
License-File: LICENSE.txt
Requires-Dist: torch>=2.2
Requires-Dist: diffusers>=0.27.2
Requires-Dist: transformers
Dynamic: author
Dynamic: author-email
Dynamic: classifier
Dynamic: description-content-type
Dynamic: home-page
Dynamic: requires-dist
Dynamic: requires-python
Dynamic: summary
